amber_data_utils/__init__.py
amber_data_utils/orchestration_utils.py
amber_data_utils/url_utils.py
amber_data_utils-0.1.3.dist-info/LICENSE.txt
amber_data_utils-0.1.3.dist-info/METADATA
amber_data_utils-0.1.3.dist-info/WHEEL
amber_data_utils-0.1.3.dist-info/RECORD
